test_mobidec_python_package_template/__init__.py
test_mobidec_python_package_template/main.py
test_mobidec_python_package_template/divider/__init__.py
test_mobidec_python_package_template/divider/divider.py
test_mobidec_python_package_template/divider/divider_error.py
test_mobidec_python_package_template-0.0.0.dist-info/METADATA
test_mobidec_python_package_template-0.0.0.dist-info/WHEEL
test_mobidec_python_package_template-0.0.0.dist-info/top_level.txt
test_mobidec_python_package_template-0.0.0.dist-info/RECORD
